sidsassignment.py
sids_basic_processor-0.0.2.dist-info/METADATA
sids_basic_processor-0.0.2.dist-info/WHEEL
sids_basic_processor-0.0.2.dist-info/top_level.txt
sids_basic_processor-0.0.2.dist-info/RECORD
