Metadata-Version: 2.4
Name: sids-basic-processor
Version: 0.0.2
Summary: A simple utility for text preprocessing (lower, punct removal, stop words).
Author: sidsassignment
Author-email: nikamsiddhant736@gmail.comm
Classifier: Programming Language :: Python :: 3
Classifier: License :: OSI Approved :: MIT License
Classifier: Operating System :: OS Independent
Classifier: Development Status :: 3 - Alpha
Requires-Python: >=3.7
